AutoLogging_ML/AutoLogger.py
AutoLogging_ML/__init__.py
AutoLogging_ML-1.2.4.dist-info/LICENSE
AutoLogging_ML-1.2.4.dist-info/METADATA
AutoLogging_ML-1.2.4.dist-info/WHEEL
AutoLogging_ML-1.2.4.dist-info/top_level.txt
AutoLogging_ML-1.2.4.dist-info/RECORD
