Metadata-Version: 2.1
Name: AutoLogging-ML
Version: 1.2.4
Summary: This is a python package useful for the automated logging and visulaization of metrics for machine learning tasks.
Author: Sairam Adithya
Author-email: sairamadithya2002@gmail.com
Classifier: Programming Language :: Python :: 3
Classifier: License :: OSI Approved :: MIT License
Classifier: Operating System :: OS Independent
Requires-Python: >=3.6
License-File: LICENSE
